pybitbucket37/__init__.py
pybitbucket37/auth.py
pybitbucket37/bitbucket.py
pybitbucket37/branchrestriction.py
pybitbucket37/build.py
pybitbucket37/comment.py
pybitbucket37/commit.py
pybitbucket37/consumer.py
pybitbucket37/entrypoints.py
pybitbucket37/hook.py
pybitbucket37/main.py
pybitbucket37/metadata.py
pybitbucket37/pullrequest.py
pybitbucket37/ref.py
pybitbucket37/repository.py
pybitbucket37/snippet.py
pybitbucket37/team.py
pybitbucket37/user.py
pybitbucket37-0.0.2.dist-info/LICENSE.txt
pybitbucket37-0.0.2.dist-info/METADATA
pybitbucket37-0.0.2.dist-info/WHEEL
pybitbucket37-0.0.2.dist-info/entry_points.txt
pybitbucket37-0.0.2.dist-info/top_level.txt
pybitbucket37-0.0.2.dist-info/RECORD
