Metadata-Version: 2.1
Name: pybitbucket37
Version: 0.0.2
Summary: A Python wrapper for the Bitbucket API
Home-page: https://bitbucket.org/atlassian/python-bitbucket
Author: Ian Buchanan
Author-email: ibuchanan@atlassian.com
Maintainer: Ian Buchanan
Maintainer-email: ibuchanan@atlassian.com
License: UNKNOWN
Platform: UNKNOWN
Classifier: Development Status :: 4 - Beta
Classifier: Environment :: Console
Classifier: Intended Audience :: Developers
Classifier: License :: OSI Approved :: Apache Software License
Classifier: License :: DFSG approved
Classifier: Natural Language :: English
Classifier: Operating System :: OS Independent
Classifier: Programming Language :: Python :: 2.7
Classifier: Programming Language :: Python :: 3.4
Classifier: Programming Language :: Python :: 3.5
Classifier: Programming Language :: Python :: Implementation :: CPython
Classifier: Programming Language :: Python :: Implementation :: PyPy
Classifier: Topic :: Software Development :: Version Control
Requires-Dist: six (<2,>=1.10)
Requires-Dist: future (<1,>=0.16)
Requires-Dist: requests (<3,>=2.12)
Requires-Dist: oauthlib (<3,>=2.0)
Requires-Dist: requests-oauthlib (<1,>=0.7)
Requires-Dist: uritemplate (<1,>=0.6)
Requires-Dist: simplejson (<4,>=3.10)
Requires-Dist: voluptuous (<1,>=0.9)
